nocodb/__init__.py
nocodb/api.py
nocodb/exceptions.py
nocodb/filters.py
nocodb/nocodb.py
nocodb/utils.py
nocodb/infra/__init__.py
nocodb/infra/requests_client.py
nocodb/infra/requests_client_test.py
nocodb-1.0.1.dist-info/LICENSE
nocodb-1.0.1.dist-info/METADATA
nocodb-1.0.1.dist-info/WHEEL
nocodb-1.0.1.dist-info/top_level.txt
nocodb-1.0.1.dist-info/RECORD
