Metadata-Version: 2.1
Name: nocodb
Version: 1.0.1
Summary: A package to use NocoDB API in a simple way
Home-page: https://github.com/ElChicoDePython/python-nocodb
Author: Samuel López Saura
Author-email: samuellopezsaura@gmail.com
License: MIT
Platform: UNKNOWN
Classifier: Programming Language :: Python :: 3
Classifier: License :: OSI Approved :: MIT License
Classifier: Operating System :: OS Independent
License-File: LICENSE
Requires-Dist: requests (>=2.0)
